tiny_listener/__init__.py
tiny_listener/__main__.py
tiny_listener/_typing.py
tiny_listener/context.py
tiny_listener/errors.py
tiny_listener/event.py
tiny_listener/hook.py
tiny_listener/listener.py
tiny_listener/routing.py
tiny_listener/utils.py
tiny_listener/__pycache__/__init__.cpython-38.pyc
tiny_listener/__pycache__/__main__.cpython-38.pyc
tiny_listener/__pycache__/_typing.cpython-38.pyc
tiny_listener/__pycache__/context.cpython-38.pyc
tiny_listener/__pycache__/errors.cpython-38.pyc
tiny_listener/__pycache__/event.cpython-38.pyc
tiny_listener/__pycache__/hook.cpython-38.pyc
tiny_listener/__pycache__/listener.cpython-38.pyc
tiny_listener/__pycache__/routing.cpython-38.pyc
tiny_listener/__pycache__/utils.cpython-38.pyc
tiny_listener-1.2.1.dist-info/LICENSE
tiny_listener-1.2.1.dist-info/METADATA
tiny_listener-1.2.1.dist-info/WHEEL
tiny_listener-1.2.1.dist-info/entry_points.txt
tiny_listener-1.2.1.dist-info/top_level.txt
tiny_listener-1.2.1.dist-info/RECORD
